<?xml version="1.0" encoding="UTF-8"?>
<NewsML Version="1.2">
        <Catalog Href="http://www.afp.com/dtd/AFPCatalog.xml"/>
  <NewsEnvelope>
        <DateAndTime>20131015T033200Z</DateAndTime>
        <Priority FormalName="4"/>
      </NewsEnvelope>
  <NewsItem>
    <Identification>
      <NewsIdentifier>
	        	                <ProviderId>afp.com</ProviderId>
	                <DateId>20131015</DateId>
                <NewsItemId>4e7252a0-298a-416f-a322-4a810546152b</NewsItemId>
        			        <RevisionId PreviousRevision="1" Update="N">2</RevisionId>
                <PublicIdentifier>urn:newsml:afp.com:20131015:4e7252a0-298a-416f-a322-4a810546152b:2</PublicIdentifier>
      </NewsIdentifier>
                              <NameLabel>Filipinas-sismo</NameLabel>
          </Identification>
    <NewsManagement>
      <NewsItemType FormalName="News"/>
            <FirstCreated>20131015T033140Z</FirstCreated>
            <ThisRevisionCreated>20131015T033141Z</ThisRevisionCreated>
                        <Status FormalName="Usable"/>
                </NewsManagement>
    <NewsComponent>
      <NewsLines>
        	<HeadLine>Seis muertos en terremoto en el centro de Filipinas</HeadLine>
                                                  <DateLine>Cebu (Filipinas) (AFP)</DateLine>
                <CopyrightLine>© 2013 AFP</CopyrightLine>
        <SlugLine>Filipinas-sismo</SlugLine>
              </NewsLines>
      <AdministrativeMetadata>
        <Provider>
	  <Party FormalName="afp.com" />
        </Provider>
                              </AdministrativeMetadata>
      <DescriptiveMetadata>
	<Language FormalName="es" />
                <OfInterestTo FormalName="espanol--edicion-conjunta--mundo"/>
                                <Location HowPresent="Origin">
                    <Property FormalName="Country" Value="PHL"/>
                              <Property FormalName="City" Value="Cebu"/>
                              <Property FormalName="Latitude" Value="10.31672"/>
                              <Property FormalName="Longitude" Value="123.89071"/>
                  </Location>
                                                                        <SubjectCode>
                                    <Subject FormalName="03000000"/>
                                          </SubjectCode>
                <SubjectCode>
                                            <SubjectMatter FormalName="03002000"/>
                                  </SubjectCode>
                <SubjectCode>
                                                    <SubjectDetail FormalName="03015001"/>
                          </SubjectCode>
                <SubjectCode>
                                    <Subject FormalName="03000000"/>
                                          </SubjectCode>
                      </DescriptiveMetadata>
                                                                                                              <NewsComponent>
        <ContentItem>
          <MediaType FormalName="Text"/>
          <Format FormalName="bcNITF2.5"/>
          <DataContent><media media-type="image" style="leftSide"><media-reference data-location="#photo0" mime-type=""/></media><p>Al menos seis muertos dejó un violento sismo que golpeó este martes las islas Filipinas, cerca de la turística región central de Cebu, indicaron las autoridades locales, </p><p>Cuatro personas perecieron, varias sufrieron heridas y un mercado de pescado se vino abajo, detalló Raquel Arce, administradora del mercado de la ciudad de Cebu, indicó la radio DYSS.</p><p>Otra persona perdió la vida en un mercado vecino y un niño murió en una estampida de gente presa de pánico que abandonada un edificio, indico elgobernador de Cebu, Hilario Davide, a la televisión ABS-CBN.</p><media media-type="image" style="rightSide"><media-reference data-location="#photo1" mime-type=""/></media><p>El Instituto Geofísico de Estados Unidos (USGS) anunció primero que el terremoto fue de magnitud 7,2 antes de revisarla a la baja, a 7,1.</p><p>El sismo se produjo a las 08h12 (00h12 GMT) con epicentro a unos 5 km al este de Balilihan, región de Bohol, a 56 km de profundidad, precisó la agencia estadounidense.</p><p>Enfrente de Balilihan, a unos 60 km, del otro lado del estrecho de Cebu, se encuentra la región turística de Cebu y la ciudad del mismo nombre, la quinta más poblada de Filipinas.</p><p>El USGS había emitido una alerta amarilla después del sismo e indicó que "el impacto debería estar relativamente delimitado". "Las alertas amarillas aisladas reclamaron en el pasado una respuesta local o regional", añadió el Instituto.</p><p>El terremoto fue seguido de dos réplicas, de magnitud superior a 5.</p><p>El centro de alerta de tsunamis, en el Pacífico, no emitió alerta de tsunami.</p><p>El epicentro del sismo se encuentra a 629 km de la capital, Manille.</p><p>Balilihan tiene unos 18.500 habitantes, según la página de la ciudad en internet.</p></DataContent>
        </ContentItem>
      </NewsComponent>
          
                                      <NewsComponent Duid="photo0">
            <NewsLines>
                            <HeadLine>La gente camina junto a la iglesia de San Pedro en la región de Bohol, dañada por el terremoto de magnitud 7,2 que sacudió Filipinas el 15 de octubre de 2013</HeadLine>
                            <CreditLine>AFP</CreditLine>
                            <ByLine>Robert Michael Poole</ByLine>
                                        </NewsLines>
            <AdministrativeMetadata>
              <Provider>
                                <Party FormalName="afp.com" />
                              </Provider>
              <Creator>
                <Party FormalName="Robert Michael Poole"/>
              </Creator>
                            <Source>
                <Party FormalName="AFP"/>
              </Source>
            </AdministrativeMetadata>
            <NewsComponent>
                                                                                                  <Role FormalName="Caption"/>
              <ContentItem>
                <MediaType FormalName="Text"/>
                <Format FormalName="bcNITF2.5"/>
                <DataContent><p>La gente camina junto a la iglesia de San Pedro en la región de Bohol, dañada por el terremoto de magnitud 7,2 que sacudió Filipinas el 15 de octubre de 2013</p></DataContent>
              </ContentItem>
            </NewsComponent>
                                    <NewsComponent>
                                          <Role FormalName="HighDef"/>
                            <ContentItem Href="1d5f25788c61e93cbd5bee9e4b1a88937122a418.jpg">
                <MediaType FormalName="Photo"/>
                                                                <Format FormalName="JPG"/>
                                <Characteristics>
                  <SizeInBytes>79657</SizeInBytes>
                  <Property FormalName="Width" Value="767"/>
                  <Property FormalName="Height" Value="559"/>
                </Characteristics>
              </ContentItem>
            </NewsComponent>
                                                                        <NewsComponent>
                                                        <Role FormalName="Quicklook"/>
                            <ContentItem Href="c9bd8c874fc0b9b7bf0385819e077d399b9425fe.jpg">
                <MediaType FormalName="Photo"/>
                                                <Format FormalName="JPG"/>
                                <Characteristics>
                  <SizeInBytes>12225</SizeInBytes>
                  <Property FormalName="Width" Value="244"/>
                  <Property FormalName="Height" Value="178"/>
                </Characteristics>
              </ContentItem>
            </NewsComponent>
                                                <NewsComponent>
                                          <Role FormalName="Thumbnail"/>
                            <ContentItem Href="6c3ec2f4c6a76b465239936439cf6b949d3788dc.jpg">
                <MediaType FormalName="Photo"/>
                                                <Format FormalName="JPG"/>
                                <Characteristics>
                  <SizeInBytes>3499</SizeInBytes>
                  <Property FormalName="Width" Value="110"/>
                  <Property FormalName="Height" Value="80"/>
                </Characteristics>
              </ContentItem>
            </NewsComponent>
                                                                                                          </NewsComponent>
                                                    <NewsComponent Duid="photo1">
            <NewsLines>
                            <HeadLine>Imagen de la iglesia de San Pedro, devastada por un terremoto ocurrido en las islas Filipinas, cerca de la turística región central de Cebu, el 15 de octubre de 2013</HeadLine>
                            <CreditLine>AFP</CreditLine>
                            <ByLine>Robert Michael Poole</ByLine>
                                        </NewsLines>
            <AdministrativeMetadata>
              <Provider>
                                <Party FormalName="afp.com" />
                              </Provider>
              <Creator>
                <Party FormalName="Robert Michael Poole"/>
              </Creator>
                            <Source>
                <Party FormalName="AFP"/>
              </Source>
            </AdministrativeMetadata>
            <NewsComponent>
                                                                                                  <Role FormalName="Caption"/>
              <ContentItem>
                <MediaType FormalName="Text"/>
                <Format FormalName="bcNITF2.5"/>
                <DataContent><p>Imagen de la iglesia de San Pedro, devastada por un terremoto ocurrido en las islas Filipinas, cerca de la turística región central de Cebu, el 15 de octubre de 2013</p></DataContent>
              </ContentItem>
            </NewsComponent>
                                    <NewsComponent>
                                          <Role FormalName="HighDef"/>
                            <ContentItem Href="09cca4cb3bbf87a6aaa66a56bdf35b55b63dfa49.jpg">
                <MediaType FormalName="Photo"/>
                                                <Format FormalName="JPG"/>
                                <Characteristics>
                  <SizeInBytes>73271</SizeInBytes>
                  <Property FormalName="Width" Value="768"/>
                  <Property FormalName="Height" Value="576"/>
                </Characteristics>
              </ContentItem>
            </NewsComponent>
                                                                        <NewsComponent>
                                                        <Role FormalName="Quicklook"/>
                            <ContentItem Href="cdbc2b4ae4f1f8908bd6bbf5c5fd730303dcf613.jpg">
                <MediaType FormalName="Photo"/>
                                                <Format FormalName="JPG"/>
                                <Characteristics>
                  <SizeInBytes>11012</SizeInBytes>
                  <Property FormalName="Width" Value="245"/>
                  <Property FormalName="Height" Value="184"/>
                </Characteristics>
              </ContentItem>
            </NewsComponent>
                                                <NewsComponent>
                                          <Role FormalName="Thumbnail"/>
                            <ContentItem Href="7b5ea14d62f7d83877a8df0b5c529baa446eb2fa.jpg">
                <MediaType FormalName="Photo"/>
                                                <Format FormalName="JPG"/>
                                <Characteristics>
                  <SizeInBytes>3352</SizeInBytes>
                  <Property FormalName="Width" Value="110"/>
                  <Property FormalName="Height" Value="83"/>
                </Characteristics>
              </ContentItem>
            </NewsComponent>
                                                                                                          </NewsComponent>
                                </NewsComponent>
  </NewsItem>
</NewsML>
